odoo/addons/delivery_package_default_shipping_weight/README.rst
odoo/addons/delivery_package_default_shipping_weight/__init__.py
odoo/addons/delivery_package_default_shipping_weight/__manifest__.py
odoo/addons/delivery_package_default_shipping_weight/i18n/delivery_package_default_shipping_weight.pot
odoo/addons/delivery_package_default_shipping_weight/models/__init__.py
odoo/addons/delivery_package_default_shipping_weight/models/product_packaging.py
odoo/addons/delivery_package_default_shipping_weight/models/stock_quant_package.py
odoo/addons/delivery_package_default_shipping_weight/readme/CONTRIBUTORS.rst
odoo/addons/delivery_package_default_shipping_weight/readme/CREDITS.rst
odoo/addons/delivery_package_default_shipping_weight/readme/DESCRIPTION.rst
odoo/addons/delivery_package_default_shipping_weight/static/description/icon.png
odoo/addons/delivery_package_default_shipping_weight/static/description/index.html
odoo/addons/delivery_package_default_shipping_weight/tests/__init__.py
odoo/addons/delivery_package_default_shipping_weight/tests/test_delivery_package_default_shipping_weight.py
odoo/addons/delivery_package_default_shipping_weight/views/product_packaging.xml
odoo14_addon_delivery_package_default_shipping_weight-14.0.1.0.1.dist-info/METADATA
odoo14_addon_delivery_package_default_shipping_weight-14.0.1.0.1.dist-info/WHEEL
odoo14_addon_delivery_package_default_shipping_weight-14.0.1.0.1.dist-info/top_level.txt
odoo14_addon_delivery_package_default_shipping_weight-14.0.1.0.1.dist-info/RECORD
